<?xml version="1.0" encoding="utf-8" standalone="yes"?>
<Gesture Name = "x">
	<Stroke>
		<Point X = "130,5" Y = "-218" T = "0" Pressure = "0" />
		<Point X = "130,5" Y = "-218" T = "0" Pressure = "0" />
		<Point X = "130,5" Y = "-218" T = "0" Pressure = "0" />
		<Point X = "130,5" Y = "-218" T = "0" Pressure = "0" />
		<Point X = "130,5" Y = "-218" T = "0" Pressure = "0" />
		<Point X = "130,5" Y = "-218" T = "0" Pressure = "0" />
		<Point X = "130,5" Y = "-218" T = "0" Pressure = "0" />
		<Point X = "130,5" Y = "-218" T = "0" Pressure = "0" />
		<Point X = "130,5" Y = "-218" T = "0" Pressure = "0" />
		<Point X = "130,5" Y = "-218" T = "0" Pressure = "0" />
		<Point X = "130,5" Y = "-218" T = "0" Pressure = "0" />
		<Point X = "130,5" Y = "-218" T = "0" Pressure = "0" />
		<Point X = "130,5" Y = "-218" T = "0" Pressure = "0" />
		<Point X = "130,5" Y = "-218" T = "0" Pressure = "0" />
		<Point X = "130,5" Y = "-218" T = "0" Pressure = "0" />
		<Point X = "130,5" Y = "-218" T = "0" Pressure = "0" />
		<Point X = "130,5" Y = "-218" T = "0" Pressure = "0" />
		<Point X = "130,5" Y = "-218" T = "0" Pressure = "0" />
		<Point X = "130,5" Y = "-218" T = "0" Pressure = "0" />
		<Point X = "130,5" Y = "-218" T = "0" Pressure = "0" />
		<Point X = "130,5" Y = "-218" T = "0" Pressure = "0" />
		<Point X = "130,5" Y = "-218" T = "0" Pressure = "0" />
		<Point X = "130,5" Y = "-218" T = "0" Pressure = "0" />
		<Point X = "130,5" Y = "-218" T = "0" Pressure = "0" />
		<Point X = "138,5" Y = "-230" T = "0" Pressure = "0" />
		<Point X = "138,5" Y = "-230" T = "0" Pressure = "0" />
		<Point X = "138,5" Y = "-230" T = "0" Pressure = "0" />
		<Point X = "138,5" Y = "-230" T = "0" Pressure = "0" />
		<Point X = "138,5" Y = "-230" T = "0" Pressure = "0" />
		<Point X = "138,5" Y = "-230" T = "0" Pressure = "0" />
		<Point X = "138,5" Y = "-230" T = "0" Pressure = "0" />
		<Point X = "152,5" Y = "-242" T = "0" Pressure = "0" />
		<Point X = "152,5" Y = "-242" T = "0" Pressure = "0" />
		<Point X = "152,5" Y = "-242" T = "0" Pressure = "0" />
		<Point X = "152,5" Y = "-242" T = "0" Pressure = "0" />
		<Point X = "152,5" Y = "-242" T = "0" Pressure = "0" />
		<Point X = "152,5" Y = "-242" T = "0" Pressure = "0" />
		<Point X = "172,5" Y = "-257" T = "0" Pressure = "0" />
		<Point X = "172,5" Y = "-257" T = "0" Pressure = "0" />
		<Point X = "172,5" Y = "-257" T = "0" Pressure = "0" />
		<Point X = "172,5" Y = "-257" T = "0" Pressure = "0" />
		<Point X = "172,5" Y = "-257" T = "0" Pressure = "0" />
		<Point X = "172,5" Y = "-257" T = "0" Pressure = "0" />
		<Point X = "195,5" Y = "-274" T = "0" Pressure = "0" />
		<Point X = "195,5" Y = "-274" T = "0" Pressure = "0" />
		<Point X = "195,5" Y = "-274" T = "0" Pressure = "0" />
		<Point X = "195,5" Y = "-274" T = "0" Pressure = "0" />
		<Point X = "195,5" Y = "-274" T = "0" Pressure = "0" />
		<Point X = "195,5" Y = "-274" T = "0" Pressure = "0" />
		<Point X = "221,5" Y = "-293" T = "0" Pressure = "0" />
		<Point X = "221,5" Y = "-293" T = "0" Pressure = "0" />
		<Point X = "221,5" Y = "-293" T = "0" Pressure = "0" />
		<Point X = "221,5" Y = "-293" T = "0" Pressure = "0" />
		<Point X = "221,5" Y = "-293" T = "0" Pressure = "0" />
		<Point X = "221,5" Y = "-293" T = "0" Pressure = "0" />
		<Point X = "252,5" Y = "-313" T = "0" Pressure = "0" />
		<Point X = "252,5" Y = "-313" T = "0" Pressure = "0" />
		<Point X = "252,5" Y = "-313" T = "0" Pressure = "0" />
		<Point X = "252,5" Y = "-313" T = "0" Pressure = "0" />
		<Point X = "252,5" Y = "-313" T = "0" Pressure = "0" />
		<Point X = "252,5" Y = "-313" T = "0" Pressure = "0" />
		<Point X = "286,5" Y = "-331" T = "0" Pressure = "0" />
		<Point X = "286,5" Y = "-331" T = "0" Pressure = "0" />
		<Point X = "286,5" Y = "-331" T = "0" Pressure = "0" />
		<Point X = "286,5" Y = "-331" T = "0" Pressure = "0" />
		<Point X = "286,5" Y = "-331" T = "0" Pressure = "0" />
		<Point X = "286,5" Y = "-331" T = "0" Pressure = "0" />
		<Point X = "286,5" Y = "-331" T = "0" Pressure = "0" />
		<Point X = "318,5" Y = "-353" T = "0" Pressure = "0" />
		<Point X = "318,5" Y = "-353" T = "0" Pressure = "0" />
		<Point X = "318,5" Y = "-353" T = "0" Pressure = "0" />
		<Point X = "318,5" Y = "-353" T = "0" Pressure = "0" />
		<Point X = "349,5" Y = "-374" T = "0" Pressure = "0" />
		<Point X = "349,5" Y = "-374" T = "0" Pressure = "0" />
		<Point X = "349,5" Y = "-374" T = "0" Pressure = "0" />
		<Point X = "349,5" Y = "-374" T = "0" Pressure = "0" />
		<Point X = "349,5" Y = "-374" T = "0" Pressure = "0" />
		<Point X = "349,5" Y = "-374" T = "0" Pressure = "0" />
		<Point X = "349,5" Y = "-374" T = "0" Pressure = "0" />
		<Point X = "375,5" Y = "-393" T = "0" Pressure = "0" />
		<Point X = "375,5" Y = "-393" T = "0" Pressure = "0" />
		<Point X = "375,5" Y = "-393" T = "0" Pressure = "0" />
		<Point X = "375,5" Y = "-393" T = "0" Pressure = "0" />
		<Point X = "375,5" Y = "-393" T = "0" Pressure = "0" />
		<Point X = "375,5" Y = "-393" T = "0" Pressure = "0" />
		<Point X = "392,5" Y = "-408" T = "0" Pressure = "0" />
		<Point X = "392,5" Y = "-408" T = "0" Pressure = "0" />
		<Point X = "392,5" Y = "-408" T = "0" Pressure = "0" />
		<Point X = "392,5" Y = "-408" T = "0" Pressure = "0" />
		<Point X = "392,5" Y = "-408" T = "0" Pressure = "0" />
		<Point X = "392,5" Y = "-408" T = "0" Pressure = "0" />
		<Point X = "392,5" Y = "-408" T = "0" Pressure = "0" />
		<Point X = "402,5" Y = "-419" T = "0" Pressure = "0" />
		<Point X = "402,5" Y = "-419" T = "0" Pressure = "0" />
		<Point X = "402,5" Y = "-419" T = "0" Pressure = "0" />
		<Point X = "402,5" Y = "-419" T = "0" Pressure = "0" />
		<Point X = "402,5" Y = "-419" T = "0" Pressure = "0" />
		<Point X = "402,5" Y = "-419" T = "0" Pressure = "0" />
		<Point X = "404,5" Y = "-424" T = "0" Pressure = "0" />
		<Point X = "404,5" Y = "-424" T = "0" Pressure = "0" />
		<Point X = "404,5" Y = "-424" T = "0" Pressure = "0" />
		<Point X = "404,5" Y = "-424" T = "0" Pressure = "0" />
		<Point X = "404,5" Y = "-424" T = "0" Pressure = "0" />
		<Point X = "404,5" Y = "-424" T = "0" Pressure = "0" />
		<Point X = "404,5" Y = "-424" T = "0" Pressure = "0" />
		<Point X = "405,5" Y = "-426" T = "0" Pressure = "0" />
		<Point X = "405,5" Y = "-426" T = "0" Pressure = "0" />
		<Point X = "405,5" Y = "-426" T = "0" Pressure = "0" />
		<Point X = "405,5" Y = "-426" T = "0" Pressure = "0" />
		<Point X = "405,5" Y = "-426" T = "0" Pressure = "0" />
		<Point X = "405,5" Y = "-426" T = "0" Pressure = "0" />
	</Stroke>
	<Stroke>
		<Point X = "167,5" Y = "-410" T = "0" Pressure = "0" />
		<Point X = "167,5" Y = "-410" T = "0" Pressure = "0" />
		<Point X = "167,5" Y = "-410" T = "0" Pressure = "0" />
		<Point X = "167,5" Y = "-410" T = "0" Pressure = "0" />
		<Point X = "167,5" Y = "-410" T = "0" Pressure = "0" />
		<Point X = "167,5" Y = "-410" T = "0" Pressure = "0" />
		<Point X = "167,5" Y = "-410" T = "0" Pressure = "0" />
		<Point X = "167,5" Y = "-410" T = "0" Pressure = "0" />
		<Point X = "167,5" Y = "-410" T = "0" Pressure = "0" />
		<Point X = "167,5" Y = "-410" T = "0" Pressure = "0" />
		<Point X = "167,5" Y = "-410" T = "0" Pressure = "0" />
		<Point X = "167,5" Y = "-410" T = "0" Pressure = "0" />
		<Point X = "167,5" Y = "-410" T = "0" Pressure = "0" />
		<Point X = "167,5" Y = "-410" T = "0" Pressure = "0" />
		<Point X = "167,5" Y = "-410" T = "0" Pressure = "0" />
		<Point X = "167,5" Y = "-410" T = "0" Pressure = "0" />
		<Point X = "167,5" Y = "-410" T = "0" Pressure = "0" />
		<Point X = "167,5" Y = "-410" T = "0" Pressure = "0" />
		<Point X = "167,5" Y = "-410" T = "0" Pressure = "0" />
		<Point X = "167,5" Y = "-410" T = "0" Pressure = "0" />
		<Point X = "167,5" Y = "-410" T = "0" Pressure = "0" />
		<Point X = "167,5" Y = "-410" T = "0" Pressure = "0" />
		<Point X = "167,5" Y = "-410" T = "0" Pressure = "0" />
		<Point X = "167,5" Y = "-410" T = "0" Pressure = "0" />
		<Point X = "167,5" Y = "-410" T = "0" Pressure = "0" />
		<Point X = "167,5" Y = "-410" T = "0" Pressure = "0" />
		<Point X = "167,5" Y = "-410" T = "0" Pressure = "0" />
		<Point X = "167,5" Y = "-410" T = "0" Pressure = "0" />
		<Point X = "167,5" Y = "-410" T = "0" Pressure = "0" />
		<Point X = "167,5" Y = "-410" T = "0" Pressure = "0" />
		<Point X = "167,5" Y = "-410" T = "0" Pressure = "0" />
		<Point X = "167,5" Y = "-410" T = "0" Pressure = "0" />
		<Point X = "167,5" Y = "-410" T = "0" Pressure = "0" />
		<Point X = "170,5" Y = "-410" T = "0" Pressure = "0" />
		<Point X = "170,5" Y = "-410" T = "0" Pressure = "0" />
		<Point X = "170,5" Y = "-410" T = "0" Pressure = "0" />
		<Point X = "170,5" Y = "-410" T = "0" Pressure = "0" />
		<Point X = "170,5" Y = "-410" T = "0" Pressure = "0" />
		<Point X = "170,5" Y = "-410" T = "0" Pressure = "0" />
		<Point X = "174,5" Y = "-410" T = "0" Pressure = "0" />
		<Point X = "174,5" Y = "-410" T = "0" Pressure = "0" />
		<Point X = "174,5" Y = "-410" T = "0" Pressure = "0" />
		<Point X = "174,5" Y = "-410" T = "0" Pressure = "0" />
		<Point X = "174,5" Y = "-410" T = "0" Pressure = "0" />
		<Point X = "174,5" Y = "-410" T = "0" Pressure = "0" />
		<Point X = "180,5" Y = "-408" T = "0" Pressure = "0" />
		<Point X = "180,5" Y = "-408" T = "0" Pressure = "0" />
		<Point X = "180,5" Y = "-408" T = "0" Pressure = "0" />
		<Point X = "180,5" Y = "-408" T = "0" Pressure = "0" />
		<Point X = "180,5" Y = "-408" T = "0" Pressure = "0" />
		<Point X = "180,5" Y = "-408" T = "0" Pressure = "0" />
		<Point X = "184,5" Y = "-403" T = "0" Pressure = "0" />
		<Point X = "184,5" Y = "-403" T = "0" Pressure = "0" />
		<Point X = "184,5" Y = "-403" T = "0" Pressure = "0" />
		<Point X = "184,5" Y = "-403" T = "0" Pressure = "0" />
		<Point X = "184,5" Y = "-403" T = "0" Pressure = "0" />
		<Point X = "184,5" Y = "-403" T = "0" Pressure = "0" />
		<Point X = "184,5" Y = "-403" T = "0" Pressure = "0" />
		<Point X = "193,5" Y = "-394" T = "0" Pressure = "0" />
		<Point X = "193,5" Y = "-394" T = "0" Pressure = "0" />
		<Point X = "193,5" Y = "-394" T = "0" Pressure = "0" />
		<Point X = "193,5" Y = "-394" T = "0" Pressure = "0" />
		<Point X = "193,5" Y = "-394" T = "0" Pressure = "0" />
		<Point X = "193,5" Y = "-394" T = "0" Pressure = "0" />
		<Point X = "207,5" Y = "-381" T = "0" Pressure = "0" />
		<Point X = "207,5" Y = "-381" T = "0" Pressure = "0" />
		<Point X = "207,5" Y = "-381" T = "0" Pressure = "0" />
		<Point X = "207,5" Y = "-381" T = "0" Pressure = "0" />
		<Point X = "207,5" Y = "-381" T = "0" Pressure = "0" />
		<Point X = "224,5" Y = "-367" T = "0" Pressure = "0" />
		<Point X = "224,5" Y = "-367" T = "0" Pressure = "0" />
		<Point X = "224,5" Y = "-367" T = "0" Pressure = "0" />
		<Point X = "224,5" Y = "-367" T = "0" Pressure = "0" />
		<Point X = "224,5" Y = "-367" T = "0" Pressure = "0" />
		<Point X = "224,5" Y = "-367" T = "0" Pressure = "0" />
		<Point X = "246,5" Y = "-348" T = "0" Pressure = "0" />
		<Point X = "246,5" Y = "-348" T = "0" Pressure = "0" />
		<Point X = "246,5" Y = "-348" T = "0" Pressure = "0" />
		<Point X = "246,5" Y = "-348" T = "0" Pressure = "0" />
		<Point X = "246,5" Y = "-348" T = "0" Pressure = "0" />
		<Point X = "246,5" Y = "-348" T = "0" Pressure = "0" />
		<Point X = "246,5" Y = "-348" T = "0" Pressure = "0" />
		<Point X = "265,5" Y = "-334" T = "0" Pressure = "0" />
		<Point X = "265,5" Y = "-334" T = "0" Pressure = "0" />
		<Point X = "265,5" Y = "-334" T = "0" Pressure = "0" />
		<Point X = "265,5" Y = "-334" T = "0" Pressure = "0" />
		<Point X = "265,5" Y = "-334" T = "0" Pressure = "0" />
		<Point X = "284,5" Y = "-321" T = "0" Pressure = "0" />
		<Point X = "284,5" Y = "-321" T = "0" Pressure = "0" />
		<Point X = "284,5" Y = "-321" T = "0" Pressure = "0" />
		<Point X = "284,5" Y = "-321" T = "0" Pressure = "0" />
		<Point X = "284,5" Y = "-321" T = "0" Pressure = "0" />
		<Point X = "284,5" Y = "-321" T = "0" Pressure = "0" />
		<Point X = "302,5" Y = "-308" T = "0" Pressure = "0" />
		<Point X = "302,5" Y = "-308" T = "0" Pressure = "0" />
		<Point X = "302,5" Y = "-308" T = "0" Pressure = "0" />
		<Point X = "302,5" Y = "-308" T = "0" Pressure = "0" />
		<Point X = "302,5" Y = "-308" T = "0" Pressure = "0" />
		<Point X = "302,5" Y = "-308" T = "0" Pressure = "0" />
		<Point X = "302,5" Y = "-308" T = "0" Pressure = "0" />
		<Point X = "316,5" Y = "-297" T = "0" Pressure = "0" />
		<Point X = "316,5" Y = "-297" T = "0" Pressure = "0" />
		<Point X = "316,5" Y = "-297" T = "0" Pressure = "0" />
		<Point X = "316,5" Y = "-297" T = "0" Pressure = "0" />
		<Point X = "316,5" Y = "-297" T = "0" Pressure = "0" />
		<Point X = "316,5" Y = "-297" T = "0" Pressure = "0" />
		<Point X = "330,5" Y = "-287" T = "0" Pressure = "0" />
		<Point X = "330,5" Y = "-287" T = "0" Pressure = "0" />
		<Point X = "330,5" Y = "-287" T = "0" Pressure = "0" />
		<Point X = "330,5" Y = "-287" T = "0" Pressure = "0" />
		<Point X = "330,5" Y = "-287" T = "0" Pressure = "0" />
		<Point X = "330,5" Y = "-287" T = "0" Pressure = "0" />
		<Point X = "330,5" Y = "-287" T = "0" Pressure = "0" />
		<Point X = "343,5" Y = "-276" T = "0" Pressure = "0" />
		<Point X = "343,5" Y = "-276" T = "0" Pressure = "0" />
		<Point X = "343,5" Y = "-276" T = "0" Pressure = "0" />
		<Point X = "343,5" Y = "-276" T = "0" Pressure = "0" />
		<Point X = "343,5" Y = "-276" T = "0" Pressure = "0" />
		<Point X = "343,5" Y = "-276" T = "0" Pressure = "0" />
		<Point X = "354,5" Y = "-264" T = "0" Pressure = "0" />
		<Point X = "354,5" Y = "-264" T = "0" Pressure = "0" />
		<Point X = "354,5" Y = "-264" T = "0" Pressure = "0" />
		<Point X = "354,5" Y = "-264" T = "0" Pressure = "0" />
		<Point X = "354,5" Y = "-264" T = "0" Pressure = "0" />
		<Point X = "354,5" Y = "-264" T = "0" Pressure = "0" />
		<Point X = "365,5" Y = "-251" T = "0" Pressure = "0" />
		<Point X = "365,5" Y = "-251" T = "0" Pressure = "0" />
		<Point X = "365,5" Y = "-251" T = "0" Pressure = "0" />
		<Point X = "365,5" Y = "-251" T = "0" Pressure = "0" />
		<Point X = "365,5" Y = "-251" T = "0" Pressure = "0" />
		<Point X = "365,5" Y = "-251" T = "0" Pressure = "0" />
		<Point X = "365,5" Y = "-251" T = "0" Pressure = "0" />
		<Point X = "375,5" Y = "-238" T = "0" Pressure = "0" />
		<Point X = "375,5" Y = "-238" T = "0" Pressure = "0" />
		<Point X = "375,5" Y = "-238" T = "0" Pressure = "0" />
		<Point X = "375,5" Y = "-238" T = "0" Pressure = "0" />
		<Point X = "375,5" Y = "-238" T = "0" Pressure = "0" />
		<Point X = "375,5" Y = "-238" T = "0" Pressure = "0" />
		<Point X = "379,5" Y = "-229" T = "0" Pressure = "0" />
		<Point X = "379,5" Y = "-229" T = "0" Pressure = "0" />
		<Point X = "379,5" Y = "-229" T = "0" Pressure = "0" />
		<Point X = "379,5" Y = "-229" T = "0" Pressure = "0" />
		<Point X = "379,5" Y = "-229" T = "0" Pressure = "0" />
		<Point X = "379,5" Y = "-229" T = "0" Pressure = "0" />
		<Point X = "379,5" Y = "-229" T = "0" Pressure = "0" />
		<Point X = "385,5" Y = "-217" T = "0" Pressure = "0" />
		<Point X = "385,5" Y = "-217" T = "0" Pressure = "0" />
		<Point X = "385,5" Y = "-217" T = "0" Pressure = "0" />
		<Point X = "385,5" Y = "-217" T = "0" Pressure = "0" />
		<Point X = "385,5" Y = "-217" T = "0" Pressure = "0" />
		<Point X = "385,5" Y = "-217" T = "0" Pressure = "0" />
		<Point X = "391,5" Y = "-205" T = "0" Pressure = "0" />
		<Point X = "391,5" Y = "-205" T = "0" Pressure = "0" />
		<Point X = "391,5" Y = "-205" T = "0" Pressure = "0" />
		<Point X = "391,5" Y = "-205" T = "0" Pressure = "0" />
		<Point X = "391,5" Y = "-205" T = "0" Pressure = "0" />
		<Point X = "391,5" Y = "-205" T = "0" Pressure = "0" />
		<Point X = "391,5" Y = "-205" T = "0" Pressure = "0" />
		<Point X = "395,5" Y = "-200" T = "0" Pressure = "0" />
		<Point X = "395,5" Y = "-200" T = "0" Pressure = "0" />
		<Point X = "395,5" Y = "-200" T = "0" Pressure = "0" />
		<Point X = "395,5" Y = "-200" T = "0" Pressure = "0" />
		<Point X = "395,5" Y = "-200" T = "0" Pressure = "0" />
		<Point X = "395,5" Y = "-200" T = "0" Pressure = "0" />
		<Point X = "398,5" Y = "-197" T = "0" Pressure = "0" />
		<Point X = "398,5" Y = "-197" T = "0" Pressure = "0" />
		<Point X = "398,5" Y = "-197" T = "0" Pressure = "0" />
		<Point X = "398,5" Y = "-197" T = "0" Pressure = "0" />
		<Point X = "398,5" Y = "-197" T = "0" Pressure = "0" />
		<Point X = "398,5" Y = "-197" T = "0" Pressure = "0" />
		<Point X = "401,5" Y = "-195" T = "0" Pressure = "0" />
		<Point X = "401,5" Y = "-195" T = "0" Pressure = "0" />
		<Point X = "401,5" Y = "-195" T = "0" Pressure = "0" />
		<Point X = "401,5" Y = "-195" T = "0" Pressure = "0" />
		<Point X = "401,5" Y = "-195" T = "0" Pressure = "0" />
		<Point X = "401,5" Y = "-195" T = "0" Pressure = "0" />
		<Point X = "401,5" Y = "-195" T = "0" Pressure = "0" />
		<Point X = "402,5" Y = "-195" T = "0" Pressure = "0" />
		<Point X = "402,5" Y = "-195" T = "0" Pressure = "0" />
		<Point X = "402,5" Y = "-195" T = "0" Pressure = "0" />
		<Point X = "402,5" Y = "-195" T = "0" Pressure = "0" />
		<Point X = "402,5" Y = "-195" T = "0" Pressure = "0" />
		<Point X = "402,5" Y = "-195" T = "0" Pressure = "0" />
		<Point X = "403,5" Y = "-195" T = "0" Pressure = "0" />
		<Point X = "403,5" Y = "-195" T = "0" Pressure = "0" />
		<Point X = "403,5" Y = "-195" T = "0" Pressure = "0" />
		<Point X = "403,5" Y = "-195" T = "0" Pressure = "0" />
		<Point X = "403,5" Y = "-195" T = "0" Pressure = "0" />
		<Point X = "403,5" Y = "-195" T = "0" Pressure = "0" />
		<Point X = "403,5" Y = "-195" T = "0" Pressure = "0" />
		<Point X = "403,5" Y = "-195" T = "0" Pressure = "0" />
		<Point X = "403,5" Y = "-195" T = "0" Pressure = "0" />
		<Point X = "403,5" Y = "-195" T = "0" Pressure = "0" />
		<Point X = "403,5" Y = "-195" T = "0" Pressure = "0" />
		<Point X = "403,5" Y = "-195" T = "0" Pressure = "0" />
		<Point X = "403,5" Y = "-195" T = "0" Pressure = "0" />
		<Point X = "405,5" Y = "-197" T = "0" Pressure = "0" />
		<Point X = "405,5" Y = "-197" T = "0" Pressure = "0" />
		<Point X = "405,5" Y = "-197" T = "0" Pressure = "0" />
		<Point X = "405,5" Y = "-197" T = "0" Pressure = "0" />
		<Point X = "405,5" Y = "-197" T = "0" Pressure = "0" />
		<Point X = "405,5" Y = "-197" T = "0" Pressure = "0" />
		<Point X = "406,5" Y = "-203" T = "0" Pressure = "0" />
	</Stroke>
</Gesture>
